{"v":"5.9.0","fr":60,"ip":0,"op":541,"w":1920,"h":517,"nm":"00 _Openline loop animation.mp4","ddd":0,"assets":[{"id":"comp_0","nm":"type slow","fr":60,"layers":[{"ddd":0,"ind":2,"ty":4,"nm":"Shape Layer 1","td":1,"sr":1,"ks":{"o":{"a":0,"k":100,"ix":11},"r":{"a":0,"k":0,"ix":10},"p":{"a":0,"k":[960,258.5,0],"ix":2,"l":2},"a":{"a":0,"k":[0,0,0],"ix":1,"l":2},"s":{"a":0,"k":[100,100,100],"ix":6,"l":2}},"ao":0,"shapes":[{"ty":"gr","it":[{"ind":0,"ty":"sh","ix":1,"ks":{"a":0,"k":{"i":[[73.25,0],[0,0],[0.53,-43.997],[-53.5,-0.5],[-0.666,24.878],[0.846,35.123]],"o":[[-82.759,0],[0,0],[-0.5,41.5],[52.5,0],[0.721,-26.94],[-1,-41.5]],"v":[[-441.75,-127.75],[-521,-79],[-521.5,21],[-440.5,71],[-358.221,26.94],[-358,-68]],"c":true},"ix":2},"nm":"Path 1","mn":"ADBE Vector Shape - Group","hd":false},{"ty":"st","c":{"a":0,"k":[1,0,0,1],"ix":3},"o":{"a":0,"k":100,"ix":4},"w":{"a":0,"k":57.1,"ix":5},"lc":1,"lj":1,"ml":4,"bm":0,"nm":"Stroke 1","mn":"ADBE Vector Graphic - Stroke","hd":false},{"ty":"tr","p":{"a":0,"k":[0,0],"ix":2},"a":{"a":0,"k":[0,0],"ix":1},"s":{"a":0,"k":[100,100],"ix":3},"r":{"a":0,"k":0,"ix":6},"o":{"a":0,"k":100,"ix":7},"sk":{"a":0,"k":0,"ix":4},"sa":{"a":0,"k":0,"ix":5},"nm":"Transform"}],"nm":"Shape 1","np":3,"cix":2,"bm":0,"ix":1,"mn":"ADBE Vector Group","hd":false},{"ty":"tm","s":{"a":0,"k":0,"ix":1},"e":{"a":1,"k":[{"i":{"x":[0.667],"y":[1]},"o":{"x":[0.167],"y":[0.167]},"t":0,"s":[0]},{"t":75,"s":[100]}],"ix":2},"o":{"a":1,"k":[{"i":{"x":[0.667],"y":[1]},"o":{"x":[0.167],"y":[0.167]},"t":0,"s":[-44.1]},{"t":75,"s":[0]}],"ix":3},"m":1,"ix":2,"nm":"Trim Paths 1","mn":"ADBE Vector Filter - Trim","hd":false}],"ip":0,"op":862.5,"st":0,"bm":0},{"ddd":0,"ind":3,"ty":4,"nm":"Слой 15 Outlines","tt":1,"sr":1,"ks":{"o":{"a":0,"k":100,"ix":11},"r":{"a":0,"k":0,"ix":10},"p":{"a":0,"k":[520.124,230.516,0],"ix":2,"l":2},"a":{"a":0,"k":[109.423,118.816,0],"ix":1,"l":2},"s":{"a":0,"k":[100,100,100],"ix":6,"l":2}},"ao":0,"shapes":[{"ty":"gr","it":[{"ind":0,"ty":"sh","ix":1,"ks":{"a":0,"k":{"i":[[-5.317,0.593],[-5.671,1.655],[-2.956,3.9],[0,5.909],[0,0],[8.739,4.608],[18.432,0],[8.74,-4.485],[0,-11.105],[0,0],[-3.074,-3.899],[-5.909,-1.651],[-5.317,-0.586],[-7.798,0]],"o":[[5.317,-0.586],[5.672,-1.651],[2.953,-3.899],[0,0],[0,-10.867],[-8.745,-4.608],[-18.431,0],[-8.745,4.492],[0,0],[0,5.909],[3.069,3.9],[5.672,1.655],[5.317,0.593],[7.799,0]],"v":[[20.027,78.335],[36.509,74.969],[49.446,66.638],[53.877,51.929],[53.877,-49.093],[40.763,-72.309],[-0.001,-79.222],[-40.763,-72.488],[-53.877,-49.093],[-53.877,51.929],[-49.27,66.638],[-35.801,74.969],[-19.318,78.335],[0.354,79.222]],"c":true},"ix":2},"nm":"Path 1","mn":"ADBE Vector Shape - Group","hd":false},{"ind":1,"ty":"sh","ix":2,"ks":{"a":0,"k":{"i":[[10.75,1.65],[11.576,4.022],[7.089,9.57],[0,13.706],[0,0],[-5.084,8.983],[-8.036,5.201],[-10.401,3.073],[-8.983,0.709],[-9.215,0],[-8.036,-0.826],[-9.925,-2.597],[-7.327,-4.724],[-4.962,-8.507],[0,-12.284],[0,0],[6.735,-9.216],[11.813,-4.726],[26.463,0]],"o":[[-10.756,-1.649],[-12.527,-4.253],[-7.09,-9.571],[0,0],[0,-11.342],[5.079,-8.978],[7.089,-4.486],[10.396,-3.069],[8.269,-0.709],[10.867,0],[8.031,0.83],[11.343,3.312],[7.322,4.73],[5.195,8.745],[0,0],[0,12.76],[-6.734,9.216],[-21.267,8.506],[-12.76,0]],"v":[[-35.623,116.085],[-69.12,107.578],[-98.539,86.843],[-109.173,51.929],[-109.173,-48.739],[-101.553,-79.222],[-81.88,-100.49],[-55.65,-111.831],[-26.585,-117.503],[-0.355,-118.567],[28.002,-117.326],[54.941,-112.187],[82.943,-100.135],[101.375,-80.286],[109.173,-48.739],[109.173,51.929],[99.071,84.893],[71.246,105.807],[-0.355,118.567]],"c":true},"ix":2},"nm":"Path 2","mn":"ADBE Vector Shape - Group","hd":false},{"ty":"mm","mm":1,"nm":"Merge Paths 1","mn":"ADBE Vector Filter - Merge","hd":false},{"ty":"fl","c":{"a":0,"k":[0,0,0,1],"ix":4},"o":{"a":0,"k":100,"ix":5},"r":1,"bm":0,"nm":"Fill 1","mn":"ADBE Vector Graphic - Fill","hd":false},{"ty":"tr","p":{"a":0,"k":[109.423,118.817],"ix":2},"a":{"a":0,"k":[0,0],"ix":1},"s":{"a":0,"k":[100,100],"ix":3},"r":{"a":0,"k":0,"ix":6},"o":{"a":0,"k":100,"ix":7},"sk":{"a":0,"k":0,"ix":4},"sa":{"a":0,"k":0,"ix":5},"nm":"Transform"}],"nm":"Group 1","np":4,"cix":2,"bm":0,"ix":1,"mn":"ADBE Vector Group","hd":false}],"ip":0,"op":862.5,"st":0,"bm":0},{"ddd":0,"ind":4,"ty":4,"nm":"Shape Layer 2","td":1,"sr":1,"ks":{"o":{"a":0,"k":100,"ix":11},"r":{"a":0,"k":0,"ix":10},"p":{"a":0,"k":[960,258.5,0],"ix":2,"l":2},"a":{"a":0,"k":[0,0,0],"ix":1,"l":2},"s":{"a":0,"k":[100,100,100],"ix":6,"l":2}},"ao":0,"shapes":[{"ty":"gr","it":[{"ind":0,"ty":"sh","ix":1,"ks":{"a":0,"k":{"i":[[0,13],[-21,-0.142],[0.25,-36],[0,0],[33.945,-1.934],[0,32]],"o":[[0,-13],[37,0.25],[-0.25,35.999],[0,0],[-39.5,2.25],[0,-32]],"v":[[-242,-34.5],[-205,-66.75],[-138.5,-34.25],[-139,47],[-180,74.5],[-261.5,31.25]],"c":false},"ix":2},"nm":"Path 1","mn":"ADBE Vector Shape - Group","hd":false},{"ty":"st","c":{"a":0,"k":[1,0,0,1],"ix":3},"o":{"a":0,"k":100,"ix":4},"w":{"a":0,"k":51.7,"ix":5},"lc":1,"lj":1,"ml":4,"bm":0,"nm":"Stroke 1","mn":"ADBE Vector Graphic - Stroke","hd":false},{"ty":"tr","p":{"a":0,"k":[0,0],"ix":2},"a":{"a":0,"k":[0,0],"ix":1},"s":{"a":0,"k":[100,100],"ix":3},"r":{"a":0,"k":0,"ix":6},"o":{"a":0,"k":100,"ix":7},"sk":{"a":0,"k":0,"ix":4},"sa":{"a":0,"k":0,"ix":5},"nm":"Transform"}],"nm":"Shape 1","np":3,"cix":2,"bm":0,"ix":1,"mn":"ADBE Vector Group","hd":false},{"ty":"tm","s":{"a":0,"k":0,"ix":1},"e":{"a":1,"k":[{"i":{"x":[0.667],"y":[1]},"o":{"x":[0.167],"y":[0.167]},"t":62.5,"s":[0]},{"t":127,"s":[100]}],"ix":2},"o":{"a":0,"k":0,"ix":3},"m":1,"ix":2,"nm":"Trim Paths 1","mn":"ADBE Vector Filter - Trim","hd":false}],"ip":65,"op":862.5,"st":65,"bm":0},{"ddd":0,"ind":5,"ty":4,"nm":"Слой 3 Outlines","tt":1,"sr":1,"ks":{"o":{"a":0,"k":100,"ix":11},"r":{"a":0,"k":0,"ix":10},"p":{"a":0,"k":[785.186,259.761,0],"ix":2,"l":2},"a":{"a":0,"k":[62.104,89.575,0],"ix":1,"l":2},"s":{"a":0,"k":[100,100,100],"ix":6,"l":2}},"ao":0,"shapes":[{"ty":"gr","it":[{"ind":0,"ty":"sh","ix":1,"ks":{"a":0,"k":{"i":[[1.65,6.26],[4.49,5.2],[9.09,2.37],[14.89,0],[8.98,-3.07],[3.409,-4.839],[0,0],[-1.757,3.513],[-5.08,1.66],[-9.69,0],[-4.96,-1.18],[-1.66,-3.42],[0,-7.8],[0,0],[1.89,-3.55],[5.19,-1.42],[10.16,0],[4.97,1.42],[1.77,3.54],[0.013,7.01],[0,0],[-7.567,-2.829],[-17.02,0],[-10.28,3.78],[-4.96,9.21],[0,17.02],[0,0]],"o":[[-1.66,-6.26],[-4.73,-5.2],[-9.1,-2.36],[-17.73,0],[-6.748,2.309],[0,0],[0.013,-6.537],[1.77,-3.55],[5.08,-1.65],[11.35,0],[4.96,1.19],[1.65,3.43],[0,0],[0,7.09],[-1.89,3.54],[-5.2,1.42],[-10.16,0],[-4.96,-1.42],[-1.757,-3.523],[0,0],[2.131,8.275],[7.55,2.84],[17.72,0],[10.28,-3.77],[4.97,-9.22],[0,0],[0,-10.87]],"v":[[59.374,-57.245],[50.154,-74.435],[29.424,-85.785],[-6.557,-89.325],[-46.617,-84.715],[-61.854,-73.988],[-61.854,-32.05],[-59.196,-47.145],[-48.917,-54.945],[-26.766,-57.425],[-2.307,-55.655],[7.624,-48.745],[10.104,-31.905],[10.104,31.545],[7.263,47.495],[-3.367,54.935],[-26.406,57.065],[-49.096,54.935],[-59.196,47.495],[-61.854,31.7],[-61.854,68.414],[-47.316,85.065],[-10.456,89.325],[31.544,83.645],[54.404,64.155],[61.854,24.805],[61.854,-31.545]],"c":true},"ix":2},"nm":"Path 1","mn":"ADBE Vector Shape - Group","hd":false},{"ty":"fl","c":{"a":0,"k":[0,0,0,1],"ix":4},"o":{"a":0,"k":100,"ix":5},"r":1,"bm":0,"nm":"Fill 1","mn":"ADBE Vector Graphic - Fill","hd":false},{"ty":"tr","p":{"a":0,"k":[62.103,89.575],"ix":2},"a":{"a":0,"k":[0,0],"ix":1},"s":{"a":0,"k":[100,100],"ix":3},"r":{"a":0,"k":0,"ix":6},"o":{"a":0,"k":100,"ix":7},"sk":{"a":0,"k":0,"ix":4},"sa":{"a":0,"k":0,"ix":5},"nm":"Transform"}],"nm":"Group 1","np":2,"cix":2,"bm":0,"ix":1,"mn":"ADBE Vector Group","hd":false}],"ip":15,"op":862.5,"st":15,"bm":0},{"ddd":0,"ind":6,"ty":4,"nm":"Слой 2 Outlines","sr":1,"ks":{"o":{"a":0,"k":100,"ix":11},"r":{"a":0,"k":0,"ix":10},"p":{"a":0,"k":[698.206,419.122,0],"ix":2,"l":2},"a":{"a":0,"k":[26.125,245.393,0],"ix":1,"l":2},"s":{"a":1,"k":[{"i":{"x":[0.18,0.18,0.18],"y":[1,1,1]},"o":{"x":[0.167,0.167,0.167],"y":[0,0.167,0]},"t":15,"s":[100,0,100]},{"t":90,"s":[100,100,100]}],"ix":6,"l":2}},"ao":0,"shapes":[{"ty":"gr","it":[{"ind":0,"ty":"sh","ix":1,"ks":{"a":0,"k":{"i":[[0,0],[0,0],[0,0],[0,0]],"o":[[0,0],[0,0],[0,0],[0,0]],"v":[[25.875,-122.643],[-25.875,-122.643],[-25.875,122.643],[25.875,122.643]],"c":true},"ix":2},"nm":"Path 1","mn":"ADBE Vector Shape - Group","hd":false},{"ty":"fl","c":{"a":0,"k":[0,0,0,1],"ix":4},"o":{"a":0,"k":100,"ix":5},"r":1,"bm":0,"nm":"Fill 1","mn":"ADBE Vector Graphic - Fill","hd":false},{"ty":"tr","p":{"a":0,"k":[26.125,122.893],"ix":2},"a":{"a":0,"k":[0,0],"ix":1},"s":{"a":0,"k":[100,100],"ix":3},"r":{"a":0,"k":0,"ix":6},"o":{"a":0,"k":100,"ix":7},"sk":{"a":0,"k":0,"ix":4},"sa":{"a":0,"k":0,"ix":5},"nm":"Transform"}],"nm":"Group 1","np":2,"cix":2,"bm":0,"ix":1,"mn":"ADBE Vector Group","hd":false}],"ip":15,"op":862.5,"st":15,"bm":0},{"ddd":0,"ind":7,"ty":4,"nm":"Shape Layer 3","td":1,"sr":1,"ks":{"o":{"a":0,"k":100,"ix":11},"r":{"a":0,"k":0,"ix":10},"p":{"a":0,"k":[960,258.5,0],"ix":2,"l":2},"a":{"a":0,"k":[0,0,0],"ix":1,"l":2},"s":{"a":0,"k":[100,100,100],"ix":6,"l":2}},"ao":0,"shapes":[{"ty":"gr","it":[{"ind":0,"ty":"sh","ix":1,"ks":{"a":0,"k":{"i":[[36,0],[0,46],[0,0],[-53.5,0],[0,-17.5],[0,0]],"o":[[-28.636,0],[0,-46],[0,0],[53.5,0],[0,17.5],[0,0]],"v":[[84,69],[-48.812,37.5],[-48.812,-45.5],[7,-72],[63.5,-33],[63.5,16]],"c":false},"ix":2},"nm":"Path 1","mn":"ADBE Vector Shape - Group","hd":false},{"ty":"st","c":{"a":0,"k":[1,0,0,1],"ix":3},"o":{"a":0,"k":100,"ix":4},"w":{"a":0,"k":52.5,"ix":5},"lc":1,"lj":1,"ml":4,"bm":0,"nm":"Stroke 1","mn":"ADBE Vector Graphic - Stroke","hd":false},{"ty":"tr","p":{"a":0,"k":[-2,0],"ix":2},"a":{"a":0,"k":[0,0],"ix":1},"s":{"a":0,"k":[100,100],"ix":3},"r":{"a":0,"k":0,"ix":6},"o":{"a":0,"k":100,"ix":7},"sk":{"a":0,"k":0,"ix":4},"sa":{"a":0,"k":0,"ix":5},"nm":"Transform"}],"nm":"Shape 1","np":3,"cix":2,"bm":0,"ix":1,"mn":"ADBE Vector Group","hd":false},{"ty":"tm","s":{"a":0,"k":0,"ix":1},"e":{"a":1,"k":[{"i":{"x":[0.833],"y":[0.833]},"o":{"x":[0.167],"y":[0.167]},"t":40,"s":[0]},{"t":130,"s":[100]}],"ix":2},"o":{"a":0,"k":0,"ix":3},"m":1,"ix":2,"nm":"Trim Paths 1","mn":"ADBE Vector Filter - Trim","hd":false}],"ip":42.5,"op":862.5,"st":42.5,"bm":0},{"ddd":0,"ind":8,"ty":4,"nm":"Слой 6 Outlines","tt":1,"sr":1,"ks":{"o":{"a":0,"k":100,"ix":11},"r":{"a":0,"k":0,"ix":10},"p":{"a":0,"k":[964.434,259.758,0],"ix":2,"l":2},"a":{"a":0,"k":[81.952,89.574,0],"ix":1,"l":2},"s":{"a":0,"k":[100,100,100],"ix":6,"l":2}},"ao":0,"shapes":[{"ty":"gr","it":[{"ind":0,"ty":"sh","ix":1,"ks":{"a":0,"k":{"i":[[0,0],[0,0],[12.638,9.338],[27.171,0],[13.824,-9.687],[0,-21.5],[0,0],[-60.733,0],[-21.035,4.485],[0,0],[17.014,0],[7.09,4.254],[0,9.924],[0,0],[0,0],[0,0],[0,0],[0,0],[-4.493,3.073],[-12.529,0],[-4.607,-2.836],[0,-5.671],[0,0],[0,0],[0,0]],"o":[[0,0],[0,-22.209],[-12.645,-9.332],[-28.834,0],[-13.824,9.692],[0,0],[0,37.103],[23.865,0],[0,0],[-21.268,4.962],[-18.432,0],[-7.089,-4.252],[0,0],[0,0],[0,0],[0,0],[0,0],[0,-5.433],[4.252,-2.836],[10.866,0],[4.608,2.835],[0,0],[0,0],[0,0],[0,0]],"v":[[81.703,13.824],[81.703,-28.002],[62.74,-75.322],[3.013,-89.324],[-60.966,-74.79],[-81.703,-28.002],[-81.703,33.673],[9.393,89.324],[76.741,82.589],[76.741,49.624],[19.318,57.068],[-18.964,50.686],[-29.596,29.421],[-29.596,15.385],[-29.596,13.824],[-29.596,-15.596],[-29.596,-17.45],[-29.596,-40.408],[-22.862,-53.169],[2.305,-57.423],[25.521,-53.169],[32.433,-40.408],[32.433,-17.45],[32.433,-15.596],[32.433,13.824]],"c":true},"ix":2},"nm":"Path 1","mn":"ADBE Vector Shape - Group","hd":false},{"ty":"fl","c":{"a":0,"k":[0,0,0,1],"ix":4},"o":{"a":0,"k":100,"ix":5},"r":1,"bm":0,"nm":"Fill 1","mn":"ADBE Vector Graphic - Fill","hd":false},{"ty":"tr","p":{"a":0,"k":[81.952,89.574],"ix":2},"a":{"a":0,"k":[0,0],"ix":1},"s":{"a":0,"k":[100,100],"ix":3},"r":{"a":0,"k":0,"ix":6},"o":{"a":0,"k":100,"ix":7},"sk":{"a":0,"k":0,"ix":4},"sa":{"a":0,"k":0,"ix":5},"nm":"Transform"}],"nm":"Group 1","np":2,"cix":2,"bm":0,"ix":1,"mn":"ADBE Vector Group","hd":false}],"ip":40,"op":862.5,"st":40,"bm":0},{"ddd":0,"ind":9,"ty":4,"nm":"Слой 7 Outlines","sr":1,"ks":{"o":{"a":0,"k":100,"ix":11},"r":{"a":0,"k":0,"ix":10},"p":{"a":0,"k":[1045.684,258.872,0],"ix":2,"l":2},"a":{"a":0,"k":[163.202,14.96,0],"ix":1,"l":2},"s":{"a":1,"k":[{"i":{"x":[0.18,0.18,0.18],"y":[1,1,1]},"o":{"x":[0.167,0.167,0.167],"y":[0.167,0,0]},"t":130,"s":[29,100,100]},{"t":197.5,"s":[100,100,100]}],"ix":6,"l":2}},"ao":0,"shapes":[{"ty":"gr","it":[{"ind":0,"ty":"sh","ix":1,"ks":{"a":0,"k":{"i":[[0,0],[0,0],[0,0],[0,0]],"o":[[0,0],[0,0],[0,0],[0,0]],"v":[[-81.702,-14.71],[81.702,-14.71],[81.702,14.71],[-81.702,14.71]],"c":true},"ix":2},"nm":"Path 1","mn":"ADBE Vector Shape - Group","hd":false},{"ty":"fl","c":{"a":0,"k":[0,0,0,1],"ix":4},"o":{"a":0,"k":100,"ix":5},"r":1,"bm":0,"nm":"Fill 1","mn":"ADBE Vector Graphic - Fill","hd":false},{"ty":"tr","p":{"a":0,"k":[81.952,14.96],"ix":2},"a":{"a":0,"k":[0,0],"ix":1},"s":{"a":0,"k":[100,100],"ix":3},"r":{"a":0,"k":0,"ix":6},"o":{"a":0,"k":100,"ix":7},"sk":{"a":0,"k":0,"ix":4},"sa":{"a":0,"k":0,"ix":5},"nm":"Transform"}],"nm":"Group 1","np":2,"cix":2,"bm":0,"ix":1,"mn":"ADBE Vector Group","hd":false}],"ip":130,"op":817.5,"st":130,"bm":0},{"ddd":0,"ind":10,"ty":4,"nm":"Shape Layer 4","td":1,"sr":1,"ks":{"o":{"a":0,"k":100,"ix":11},"r":{"a":0,"k":0,"ix":10},"p":{"a":0,"k":[1168.75,266.719,0],"ix":2,"l":2},"a":{"a":0,"k":[-200.75,8.219,0],"ix":1,"l":2},"s":{"a":0,"k":[100,100,100],"ix":6,"l":2}},"ao":0,"shapes":[{"ty":"gr","it":[{"ind":0,"ty":"sh","ix":1,"ks":{"a":0,"k":{"i":[[0,13],[-33.5,0],[0,-36],[0,0]],"o":[[0,-13],[38.5,0],[0,36],[0,0]],"v":[[-250.5,-34.5],[-202,-70],[-138,-37],[-138,86.5]],"c":false},"ix":2},"nm":"Path 1","mn":"ADBE Vector Shape - Group","hd":false},{"ty":"st","c":{"a":0,"k":[1,0,0,1],"ix":3},"o":{"a":0,"k":100,"ix":4},"w":{"a":0,"k":52.3,"ix":5},"lc":1,"lj":1,"ml":4,"bm":0,"nm":"Stroke 1","mn":"ADBE Vector Graphic - Stroke","hd":false},{"ty":"tr","p":{"a":0,"k":[-6.5,0],"ix":2},"a":{"a":0,"k":[0,0],"ix":1},"s":{"a":0,"k":[100,100],"ix":3},"r":{"a":0,"k":0,"ix":6},"o":{"a":0,"k":100,"ix":7},"sk":{"a":0,"k":0,"ix":4},"sa":{"a":0,"k":0,"ix":5},"nm":"Transform"}],"nm":"Shape 1","np":3,"cix":2,"bm":0,"ix":1,"mn":"ADBE Vector Group","hd":false},{"ty":"tm","s":{"a":0,"k":0,"ix":1},"e":{"a":1,"k":[{"i":{"x":[0.667],"y":[1]},"o":{"x":[0.167],"y":[0.167]},"t":120,"s":[0]},{"t":195,"s":[100]}],"ix":2},"o":{"a":0,"k":0,"ix":3},"m":1,"ix":2,"nm":"Trim Paths 1","mn":"ADBE Vector Filter - Trim","hd":false}],"ip":122.5,"op":862.5,"st":122.5,"bm":0},{"ddd":0,"ind":11,"ty":4,"nm":"Слой 11 Outlines","tt":1,"sr":1,"ks":{"o":{"a":0,"k":100,"ix":11},"r":{"a":0,"k":0,"ix":10},"p":{"a":0,"k":[1194.475,257.986,0],"ix":2,"l":2},"a":{"a":0,"k":[57.14,87.801,0],"ix":1,"l":2},"s":{"a":0,"k":[100,100,100],"ix":6,"l":2}},"ao":0,"shapes":[{"ty":"gr","it":[{"ind":0,"ty":"sh","ix":1,"ks":{"a":0,"k":{"i":[[8.862,7.92],[21.976,0],[4.015,-16.305],[0,0],[-1.651,3.304],[-4.73,1.302],[-10.163,0],[-3.9,-1.418],[-1.301,-3.306],[0,-6.613],[0,0],[0,0],[0,0]],"o":[[-8.861,-7.914],[-32.61,0],[0,0],[0.004,-6.825],[1.651,-3.306],[4.724,-1.295],[8.031,0],[3.899,1.418],[1.297,3.312],[0,0],[0,0],[0,0],[0,-17.014]],"v":[[43.598,-75.677],[-2.659,-87.551],[-56.89,-63.094],[-56.89,-31.598],[-54.41,-46.789],[-44.84,-53.701],[-22.509,-55.65],[-4.608,-53.523],[3.189,-46.434],[5.14,-31.547],[5.14,87.551],[56.89,87.551],[56.89,-38.282]],"c":true},"ix":2},"nm":"Path 1","mn":"ADBE Vector Shape - Group","hd":false},{"ty":"fl","c":{"a":0,"k":[0,0,0,1],"ix":4},"o":{"a":0,"k":100,"ix":5},"r":1,"bm":0,"nm":"Fill 1","mn":"ADBE Vector Graphic - Fill","hd":false},{"ty":"tr","p":{"a":0,"k":[57.14,87.801],"ix":2},"a":{"a":0,"k":[0,0],"ix":1},"s":{"a":0,"k":[100,100],"ix":3},"r":{"a":0,"k":0,"ix":6},"o":{"a":0,"k":100,"ix":7},"sk":{"a":0,"k":0,"ix":4},"sa":{"a":0,"k":0,"ix":5},"nm":"Transform"}],"nm":"Group 1","np":2,"cix":2,"bm":0,"ix":1,"mn":"ADBE Vector Group","hd":false}],"ip":85,"op":862.5,"st":85,"bm":0},{"ddd":0,"ind":12,"ty":4,"nm":"Слой 10 Outlines","sr":1,"ks":{"o":{"a":0,"k":100,"ix":11},"r":{"a":0,"k":0,"ix":10},"p":{"a":0,"k":[1111.709,344.758,0],"ix":2,"l":2},"a":{"a":0,"k":[26.125,171.029,0],"ix":1,"l":2},"s":{"a":1,"k":[{"i":{"x":[0.18,0.18,0.18],"y":[1,1,1]},"o":{"x":[0.167,0.167,0.167],"y":[0,0.167,0]},"t":85,"s":[100,0,100]},{"t":160,"s":[100,100,100]}],"ix":6,"l":2}},"ao":0,"shapes":[{"ty":"gr","it":[{"ind":0,"ty":"sh","ix":1,"ks":{"a":0,"k":{"i":[[0,0],[0,0],[0,0],[0,0]],"o":[[0,0],[0,0],[0,0],[0,0]],"v":[[25.875,85.779],[-25.875,85.779],[-25.875,-85.779],[25.875,-85.779]],"c":true},"ix":2},"nm":"Path 1","mn":"ADBE Vector Shape - Group","hd":false},{"ty":"fl","c":{"a":0,"k":[0,0,0,1],"ix":4},"o":{"a":0,"k":100,"ix":5},"r":1,"bm":0,"nm":"Fill 1","mn":"ADBE Vector Graphic - Fill","hd":false},{"ty":"tr","p":{"a":0,"k":[26.125,86.029],"ix":2},"a":{"a":0,"k":[0,0],"ix":1},"s":{"a":0,"k":[100,100],"ix":3},"r":{"a":0,"k":0,"ix":6},"o":{"a":0,"k":100,"ix":7},"sk":{"a":0,"k":0,"ix":4},"sa":{"a":0,"k":0,"ix":5},"nm":"Transform"}],"nm":"Group 1","np":2,"cix":2,"bm":0,"ix":1,"mn":"ADBE Vector Group","hd":false}],"ip":85,"op":862.5,"st":85,"bm":0},{"ddd":0,"ind":13,"ty":4,"nm":"Слой 14 Outlines","sr":1,"ks":{"o":{"a":0,"k":100,"ix":11},"r":{"a":0,"k":0,"ix":10},"p":{"a":0,"k":[1324.026,345.477,0],"ix":2,"l":2},"a":{"a":0,"k":[26.125,248.311,0],"ix":1,"l":2},"s":{"a":1,"k":[{"i":{"x":[0.18,0.18,0.18],"y":[1,1,1]},"o":{"x":[0.167,0.167,0.167],"y":[0,0.167,0]},"t":142.5,"s":[100,0,100]},{"t":217.5,"s":[100,100,100]}],"ix":6,"l":2}},"ao":0,"shapes":[{"ty":"gr","it":[{"ind":0,"ty":"sh","ix":1,"ks":{"a":0,"k":{"i":[[0,0],[0,0],[0,0],[0,0]],"o":[[0,0],[0,0],[0,0],[0,0]],"v":[[-25.875,-124.061],[25.875,-124.061],[25.875,124.061],[-25.875,124.061]],"c":true},"ix":2},"nm":"Path 1","mn":"ADBE Vector Shape - Group","hd":false},{"ty":"fl","c":{"a":0,"k":[0,0,0,1],"ix":4},"o":{"a":0,"k":100,"ix":5},"r":1,"bm":0,"nm":"Fill 1","mn":"ADBE Vector Graphic - Fill","hd":false},{"ty":"tr","p":{"a":0,"k":[26.125,124.311],"ix":2},"a":{"a":0,"k":[0,0],"ix":1},"s":{"a":0,"k":[100,100],"ix":3},"r":{"a":0,"k":0,"ix":6},"o":{"a":0,"k":100,"ix":7},"sk":{"a":0,"k":0,"ix":4},"sa":{"a":0,"k":0,"ix":5},"nm":"Transform"}],"nm":"Group 1","np":2,"cix":2,"bm":0,"ix":1,"mn":"ADBE Vector Group","hd":false}],"ip":142.5,"op":862.5,"st":142.5,"bm":0},{"ddd":0,"ind":14,"ty":4,"nm":"Слой 13 Outlines","sr":1,"ks":{"o":{"a":0,"k":100,"ix":11},"r":{"a":0,"k":0,"ix":10},"p":{"a":0,"k":[1423.98,345.477,0],"ix":2,"l":2},"a":{"a":0,"k":[26.125,248.311,0],"ix":1,"l":2},"s":{"a":1,"k":[{"i":{"x":[0.18,0.18,0.18],"y":[1,1,1]},"o":{"x":[0.167,0.167,0.167],"y":[0,0.167,0]},"t":177.5,"s":[100,0,100]},{"t":252.5,"s":[100,100,100]}],"ix":6,"l":2}},"ao":0,"shapes":[{"ty":"gr","it":[{"ind":0,"ty":"sh","ix":1,"ks":{"a":0,"k":{"i":[[0,0],[0,0],[0,0],[0,0]],"o":[[0,0],[0,0],[0,0],[0,0]],"v":[[-25.875,-47.497],[25.875,-47.497],[25.875,124.061],[-25.875,124.061]],"c":true},"ix":2},"nm":"Path 1","mn":"ADBE Vector Shape - Group","hd":false},{"ind":1,"ty":"sh","ix":2,"ks":{"a":0,"k":{"i":[[0,0],[0,0],[0,0],[0,0]],"o":[[0,0],[0,0],[0,0],[0,0]],"v":[[-25.875,-124.061],[25.875,-124.061],[25.875,-82.234],[-25.875,-82.234]],"c":true},"ix":2},"nm":"Path 2","mn":"ADBE Vector Shape - Group","hd":false},{"ty":"mm","mm":1,"nm":"Merge Paths 1","mn":"ADBE Vector Filter - Merge","hd":false},{"ty":"fl","c":{"a":0,"k":[0,0,0,1],"ix":4},"o":{"a":0,"k":100,"ix":5},"r":1,"bm":0,"nm":"Fill 1","mn":"ADBE Vector Graphic - Fill","hd":false},{"ty":"tr","p":{"a":0,"k":[26.125,124.311],"ix":2},"a":{"a":0,"k":[0,0],"ix":1},"s":{"a":0,"k":[100,100],"ix":3},"r":{"a":0,"k":0,"ix":6},"o":{"a":0,"k":100,"ix":7},"sk":{"a":0,"k":0,"ix":4},"sa":{"a":0,"k":0,"ix":5},"nm":"Transform"}],"nm":"Group 1","np":4,"cix":2,"bm":0,"ix":1,"mn":"ADBE Vector Group","hd":false}],"ip":177.5,"op":862.5,"st":177.5,"bm":0},{"ddd":0,"ind":15,"ty":4,"nm":"Shape Layer 5","td":1,"sr":1,"ks":{"o":{"a":0,"k":100,"ix":11},"r":{"a":0,"k":0,"ix":10},"p":{"a":0,"k":[1580.75,266.719,0],"ix":2,"l":2},"a":{"a":0,"k":[-200.75,8.219,0],"ix":1,"l":2},"s":{"a":0,"k":[100,100,100],"ix":6,"l":2}},"ao":0,"shapes":[{"ty":"gr","it":[{"ind":0,"ty":"sh","ix":1,"ks":{"a":0,"k":{"i":[[0,13],[-33.5,0],[0,-36],[0,0]],"o":[[0,-13],[38.5,0],[0,36],[0,0]],"v":[[-250.5,-34.5],[-202,-70],[-138,-37],[-138,86.5]],"c":false},"ix":2},"nm":"Path 1","mn":"ADBE Vector Shape - Group","hd":false},{"ty":"st","c":{"a":0,"k":[1,0,0,1],"ix":3},"o":{"a":0,"k":100,"ix":4},"w":{"a":0,"k":52.3,"ix":5},"lc":1,"lj":1,"ml":4,"bm":0,"nm":"Stroke 1","mn":"ADBE Vector Graphic - Stroke","hd":false},{"ty":"tr","p":{"a":0,"k":[-6.5,0],"ix":2},"a":{"a":0,"k":[0,0],"ix":1},"s":{"a":0,"k":[100,100],"ix":3},"r":{"a":0,"k":0,"ix":6},"o":{"a":0,"k":100,"ix":7},"sk":{"a":0,"k":0,"ix":4},"sa":{"a":0,"k":0,"ix":5},"nm":"Transform"}],"nm":"Shape 1","np":3,"cix":2,"bm":0,"ix":1,"mn":"ADBE Vector Group","hd":false},{"ty":"tm","s":{"a":0,"k":0,"ix":1},"e":{"a":1,"k":[{"i":{"x":[0.667],"y":[1]},"o":{"x":[0.167],"y":[0.167]},"t":225,"s":[0]},{"t":300,"s":[100]}],"ix":2},"o":{"a":0,"k":0,"ix":3},"m":1,"ix":2,"nm":"Trim Paths 1","mn":"ADBE Vector Filter - Trim","hd":false}],"ip":225,"op":862.5,"st":225,"bm":0},{"ddd":0,"ind":16,"ty":4,"nm":"Слой 9 Outlines","tt":1,"sr":1,"ks":{"o":{"a":0,"k":100,"ix":11},"r":{"a":0,"k":0,"ix":10},"p":{"a":0,"k":[1605.285,257.986,0],"ix":2,"l":2},"a":{"a":0,"k":[57.14,87.801,0],"ix":1,"l":2},"s":{"a":0,"k":[100,100,100],"ix":6,"l":2}},"ao":0,"shapes":[{"ty":"gr","it":[{"ind":0,"ty":"sh","ix":1,"ks":{"a":0,"k":{"i":[[8.861,7.92],[21.976,0],[4.015,-16.305],[0,0],[-1.651,3.304],[-4.73,1.302],[-10.163,0],[-3.9,-1.418],[-1.301,-3.306],[0,-6.613],[0,0],[0,0],[0,0]],"o":[[-8.861,-7.914],[-32.61,0],[0,0],[0.004,-6.825],[1.651,-3.306],[4.724,-1.295],[8.031,0],[3.899,1.418],[1.297,3.312],[0,0],[0,0],[0,0],[0,-17.014]],"v":[[43.598,-75.677],[-2.659,-87.551],[-56.89,-63.094],[-56.89,-31.598],[-54.41,-46.789],[-44.84,-53.701],[-22.509,-55.65],[-4.608,-53.523],[3.189,-46.434],[5.139,-31.547],[5.139,87.551],[56.89,87.551],[56.89,-38.282]],"c":true},"ix":2},"nm":"Path 1","mn":"ADBE Vector Shape - Group","hd":false},{"ty":"fl","c":{"a":0,"k":[0,0,0,1],"ix":4},"o":{"a":0,"k":100,"ix":5},"r":1,"bm":0,"nm":"Fill 1","mn":"ADBE Vector Graphic - Fill","hd":false},{"ty":"tr","p":{"a":0,"k":[57.14,87.801],"ix":2},"a":{"a":0,"k":[0,0],"ix":1},"s":{"a":0,"k":[100,100],"ix":3},"r":{"a":0,"k":0,"ix":6},"o":{"a":0,"k":100,"ix":7},"sk":{"a":0,"k":0,"ix":4},"sa":{"a":0,"k":0,"ix":5},"nm":"Transform"}],"nm":"Group 1","np":2,"cix":2,"bm":0,"ix":1,"mn":"ADBE Vector Group","hd":false}],"ip":192.5,"op":862.5,"st":192.5,"bm":0},{"ddd":0,"ind":17,"ty":4,"nm":"Слой 8 Outlines","sr":1,"ks":{"o":{"a":0,"k":100,"ix":11},"r":{"a":0,"k":0,"ix":10},"p":{"a":0,"k":[1522.519,345.758,0],"ix":2,"l":2},"a":{"a":0,"k":[26.126,172.029,0],"ix":1,"l":2},"s":{"a":1,"k":[{"i":{"x":[0.18,0.18,0.18],"y":[1,1,1]},"o":{"x":[0.167,0.167,0.167],"y":[0,0.167,0]},"t":192.5,"s":[100,0,100]},{"t":267.5,"s":[100,100,100]}],"ix":6,"l":2}},"ao":0,"shapes":[{"ty":"gr","it":[{"ind":0,"ty":"sh","ix":1,"ks":{"a":0,"k":{"i":[[0,0],[0,0],[0,0],[0,0]],"o":[[0,0],[0,0],[0,0],[0,0]],"v":[[25.876,85.779],[-25.876,85.779],[-25.876,-85.779],[25.876,-85.779]],"c":true},"ix":2},"nm":"Path 1","mn":"ADBE Vector Shape - Group","hd":false},{"ty":"fl","c":{"a":0,"k":[0,0,0,1],"ix":4},"o":{"a":0,"k":100,"ix":5},"r":1,"bm":0,"nm":"Fill 1","mn":"ADBE Vector Graphic - Fill","hd":false},{"ty":"tr","p":{"a":0,"k":[26.126,86.029],"ix":2},"a":{"a":0,"k":[0,0],"ix":1},"s":{"a":0,"k":[100,100],"ix":3},"r":{"a":0,"k":0,"ix":6},"o":{"a":0,"k":100,"ix":7},"sk":{"a":0,"k":0,"ix":4},"sa":{"a":0,"k":0,"ix":5},"nm":"Transform"}],"nm":"Group 1","np":2,"cix":2,"bm":0,"ix":1,"mn":"ADBE Vector Group","hd":false}],"ip":192.5,"op":862.5,"st":192.5,"bm":0},{"ddd":0,"ind":18,"ty":4,"nm":"Shape Layer 6","td":1,"sr":1,"ks":{"o":{"a":0,"k":100,"ix":11},"r":{"a":0,"k":0,"ix":10},"p":{"a":0,"k":[1780,258.5,0],"ix":2,"l":2},"a":{"a":0,"k":[0,0,0],"ix":1,"l":2},"s":{"a":0,"k":[100,100,100],"ix":6,"l":2}},"ao":0,"shapes":[{"ty":"gr","it":[{"ind":0,"ty":"sh","ix":1,"ks":{"a":0,"k":{"i":[[36,0],[0,46],[0,0],[-53.5,0],[0,-17.5],[0,0]],"o":[[-28.636,0],[0,-46],[0,0],[53.5,0],[0,17.5],[0,0]],"v":[[84,69],[-48.812,37.5],[-48.812,-45.5],[7,-72],[63.5,-33],[63.5,16]],"c":false},"ix":2},"nm":"Path 1","mn":"ADBE Vector Shape - Group","hd":false},{"ty":"st","c":{"a":0,"k":[1,0,0,1],"ix":3},"o":{"a":0,"k":100,"ix":4},"w":{"a":0,"k":52.5,"ix":5},"lc":1,"lj":1,"ml":4,"bm":0,"nm":"Stroke 1","mn":"ADBE Vector Graphic - Stroke","hd":false},{"ty":"tr","p":{"a":0,"k":[-2,0],"ix":2},"a":{"a":0,"k":[0,0],"ix":1},"s":{"a":0,"k":[100,100],"ix":3},"r":{"a":0,"k":0,"ix":6},"o":{"a":0,"k":100,"ix":7},"sk":{"a":0,"k":0,"ix":4},"sa":{"a":0,"k":0,"ix":5},"nm":"Transform"}],"nm":"Shape 1","np":3,"cix":2,"bm":0,"ix":1,"mn":"ADBE Vector Group","hd":false},{"ty":"tm","s":{"a":0,"k":0,"ix":1},"e":{"a":1,"k":[{"i":{"x":[0.833],"y":[0.833]},"o":{"x":[0.167],"y":[0.167]},"t":225,"s":[0]},{"t":310,"s":[100]}],"ix":2},"o":{"a":0,"k":0,"ix":3},"m":1,"ix":2,"nm":"Trim Paths 1","mn":"ADBE Vector Filter - Trim","hd":false}],"ip":225,"op":862.5,"st":225,"bm":0},{"ddd":0,"ind":19,"ty":4,"nm":"Слой 4 Outlines","tt":1,"sr":1,"ks":{"o":{"a":0,"k":100,"ix":11},"r":{"a":0,"k":0,"ix":10},"p":{"a":0,"k":[1784.282,259.758,0],"ix":2,"l":2},"a":{"a":0,"k":[81.952,89.574,0],"ix":1,"l":2},"s":{"a":0,"k":[100,100,100],"ix":6,"l":2}},"ao":0,"shapes":[{"ty":"gr","it":[{"ind":0,"ty":"sh","ix":1,"ks":{"a":0,"k":{"i":[[0,0],[0,0],[12.638,9.338],[27.171,0],[13.824,-9.687],[0,-21.5],[0,0],[-60.733,0],[-21.035,4.485],[0,0],[17.014,0],[7.09,4.254],[0,9.924],[0,0],[0,0],[0,0],[0,0],[0,0],[-4.493,3.073],[-12.529,0],[-4.607,-2.836],[0,-5.671],[0,0],[0,0],[0,0]],"o":[[0,0],[0,-22.209],[-12.645,-9.332],[-28.834,0],[-13.824,9.692],[0,0],[0,37.103],[23.865,0],[0,0],[-21.268,4.962],[-18.432,0],[-7.089,-4.252],[0,0],[0,0],[0,0],[0,0],[0,0],[0,-5.433],[4.252,-2.836],[10.866,0],[4.608,2.835],[0,0],[0,0],[0,0],[0,0]],"v":[[81.703,13.824],[81.703,-28.002],[62.74,-75.322],[3.013,-89.324],[-60.967,-74.79],[-81.703,-28.002],[-81.703,33.673],[9.392,89.324],[76.741,82.589],[76.741,49.624],[19.318,57.068],[-18.964,50.686],[-29.597,29.421],[-29.597,15.385],[-29.597,13.824],[-29.597,-15.596],[-29.597,-17.45],[-29.597,-40.408],[-22.862,-53.169],[2.304,-57.423],[25.521,-53.169],[32.433,-40.408],[32.433,-17.45],[32.433,-15.596],[32.433,13.824]],"c":true},"ix":2},"nm":"Path 1","mn":"ADBE Vector Shape - Group","hd":false},{"ty":"fl","c":{"a":0,"k":[0,0,0,1],"ix":4},"o":{"a":0,"k":100,"ix":5},"r":1,"bm":0,"nm":"Fill 1","mn":"ADBE Vector Graphic - Fill","hd":false},{"ty":"tr","p":{"a":0,"k":[81.952,89.574],"ix":2},"a":{"a":0,"k":[0,0],"ix":1},"s":{"a":0,"k":[100,100],"ix":3},"r":{"a":0,"k":0,"ix":6},"o":{"a":0,"k":100,"ix":7},"sk":{"a":0,"k":0,"ix":4},"sa":{"a":0,"k":0,"ix":5},"nm":"Transform"}],"nm":"Group 1","np":2,"cix":2,"bm":0,"ix":1,"mn":"ADBE Vector Group","hd":false}],"ip":225,"op":862.5,"st":225,"bm":0},{"ddd":0,"ind":20,"ty":4,"nm":"Слой 5 Outlines","sr":1,"ks":{"o":{"a":0,"k":100,"ix":11},"r":{"a":0,"k":0,"ix":10},"p":{"a":0,"k":[1865.281,258.872,0],"ix":2,"l":2},"a":{"a":0,"k":[162.953,14.96,0],"ix":1,"l":2},"s":{"a":1,"k":[{"i":{"x":[0.18,0.18,0.18],"y":[1,1,1]},"o":{"x":[0.167,0.167,0.167],"y":[0.167,0,0]},"t":309,"s":[0,100,100]},{"t":374,"s":[100,100,100]}],"ix":6,"l":2}},"ao":0,"shapes":[{"ty":"gr","it":[{"ind":0,"ty":"sh","ix":1,"ks":{"a":0,"k":{"i":[[0,0],[0,0],[0,0],[0,0]],"o":[[0,0],[0,0],[0,0],[0,0]],"v":[[-81.703,-14.71],[81.703,-14.71],[81.703,14.71],[-81.703,14.71]],"c":true},"ix":2},"nm":"Path 1","mn":"ADBE Vector Shape - Group","hd":false},{"ty":"fl","c":{"a":0,"k":[0,0,0,1],"ix":4},"o":{"a":0,"k":100,"ix":5},"r":1,"bm":0,"nm":"Fill 1","mn":"ADBE Vector Graphic - Fill","hd":false},{"ty":"tr","p":{"a":0,"k":[81.953,14.96],"ix":2},"a":{"a":0,"k":[0,0],"ix":1},"s":{"a":0,"k":[100,100],"ix":3},"r":{"a":0,"k":0,"ix":6},"o":{"a":0,"k":100,"ix":7},"sk":{"a":0,"k":0,"ix":4},"sa":{"a":0,"k":0,"ix":5},"nm":"Transform"}],"nm":"Group 1","np":2,"cix":2,"bm":0,"ix":1,"mn":"ADBE Vector Group","hd":false}],"ip":309,"op":861.5,"st":309,"bm":0}]}],"layers":[{"ddd":0,"ind":1,"ty":4,"nm":"Слой 12 Outlines","sr":1,"ks":{"o":{"a":1,"k":[{"i":{"x":[0.667],"y":[1]},"o":{"x":[0.333],"y":[0]},"t":33.125,"s":[100]},{"i":{"x":[0.667],"y":[1]},"o":{"x":[0.333],"y":[0]},"t":66.25,"s":[0]},{"i":{"x":[0.667],"y":[1]},"o":{"x":[0.333],"y":[0]},"t":99.375,"s":[100]},{"i":{"x":[0.667],"y":[1]},"o":{"x":[0.333],"y":[0]},"t":132.5,"s":[0]},{"i":{"x":[0.667],"y":[1]},"o":{"x":[0.333],"y":[0]},"t":165.625,"s":[100]},{"i":{"x":[0.667],"y":[1]},"o":{"x":[0.333],"y":[0]},"t":198.75,"s":[0]},{"i":{"x":[0.667],"y":[1]},"o":{"x":[0.333],"y":[0]},"t":231.875,"s":[100]},{"i":{"x":[0.667],"y":[1]},"o":{"x":[0.333],"y":[0]},"t":232,"s":[100]},{"i":{"x":[0.667],"y":[1]},"o":{"x":[0.333],"y":[0]},"t":265.125,"s":[0]},{"t":298.25,"s":[100]}],"ix":11},"r":{"a":0,"k":0,"ix":10},"p":{"a":0,"k":[209.199,312.552,0],"ix":2,"l":2},"a":{"a":0,"k":[155.434,28.57,0],"ix":1,"l":2},"s":{"a":0,"k":[100,100,100],"ix":6,"l":2}},"ao":0,"shapes":[{"ty":"gr","it":[{"ind":0,"ty":"sh","ix":1,"ks":{"a":0,"k":{"i":[[-5.619,0],[0,0],[0,-5.619],[0,0],[5.619,-0.002],[13.248,0.002],[0.001,5.619],[-0.003,13.251]],"o":[[0,0],[5.619,0],[0,0],[0,5.619],[-13.251,0.002],[-5.619,-0.002],[-0.003,-13.248],[0.001,-5.618]],"v":[[-145.005,-28.321],[145.01,-28.321],[155.184,-18.146],[155.184,18.142],[145.009,28.319],[-145.006,28.319],[-155.181,18.143],[-155.181,-18.146]],"c":true},"ix":2},"nm":"Path 1","mn":"ADBE Vector Shape - Group","hd":false},{"ty":"fl","c":{"a":0,"k":[1,0.400000029919,0.086274509804,1],"ix":4},"o":{"a":0,"k":100,"ix":5},"r":1,"bm":0,"nm":"Fill 1","mn":"ADBE Vector Graphic - Fill","hd":false},{"ty":"tr","p":{"a":0,"k":[155.434,28.571],"ix":2},"a":{"a":0,"k":[0,0],"ix":1},"s":{"a":0,"k":[100,100],"ix":3},"r":{"a":0,"k":0,"ix":6},"o":{"a":0,"k":100,"ix":7},"sk":{"a":0,"k":0,"ix":4},"sa":{"a":0,"k":0,"ix":5},"nm":"Transform"}],"nm":"Group 1","np":2,"cix":2,"bm":0,"ix":1,"mn":"ADBE Vector Group","hd":false}],"ip":0,"op":862.5,"st":0,"bm":0},{"ddd":0,"ind":2,"ty":0,"nm":"type slow","refId":"comp_0","sr":0.47911832946636,"ks":{"o":{"a":0,"k":100,"ix":11},"r":{"a":0,"k":0,"ix":10},"p":{"a":0,"k":[960,258.5,0],"ix":2,"l":2},"a":{"a":0,"k":[960,258.5,0],"ix":1,"l":2},"s":{"a":0,"k":[100,100,100],"ix":6,"l":2}},"ao":0,"tm":{"a":0,"k":11.375,"ix":2},"w":1920,"h":517,"ip":0,"op":886,"st":0,"bm":0}],"markers":[]}